cyscs/__init__.py
cyscs/_direct.cpython-35m-darwin.so
cyscs/_indirect.cpython-35m-darwin.so
cyscs/_scs.py
cyscs/_util.py
cyscs/examples.py
cyscs/test/test_cone.py
cyscs/test/test_cvxpy.py
cyscs/test/test_dtype.py
cyscs/test/test_mutability.py
cyscs/test/test_package.py
cyscs/test/test_solve.py
cyscs/test/test_warm_start.py
cyscs/test/test_workspace.py
cyscs-0.1.dist-info/DESCRIPTION.rst
cyscs-0.1.dist-info/METADATA
cyscs-0.1.dist-info/RECORD
cyscs-0.1.dist-info/WHEEL
cyscs-0.1.dist-info/metadata.json
cyscs-0.1.dist-info/top_level.txt
