Metadata-Version: 2.0
Name: cyscs
Version: 0.1
Summary: CySCS: A Cython wrapper for the SCS convex optimization solver.
Home-page: http://github.com/ajfriend/cyscs
Author: AJ Friend
Author-email: ajfriend@gmail.com
License: MIT
Platform: UNKNOWN
Requires-Dist: numpy (>=1.7)
Requires-Dist: scipy (>=0.13.2)
